[
  {
    "tbinfo": "ouid=5044281310",
    "mid": "4504509860970591",
    "text": "#法工委称家暴不适用离婚冷静期#【全国人大：离婚冷静期制度仅适用于自愿离婚，家暴不适用】民法典婚姻家庭编草案明确了离婚冷静期的规定，但有观点认为，应当对离婚冷静期设立甄别机制，在家庭暴力等案件中不应设置冷静期。5月14日，全国人大常委会法工委回应称，经研究认为，离婚冷静期制度只适用于 ​​​​...¡查看图片展开全文c",
    "link": "http://weibo.com/5044281310/J1TjY44uH?from=page_1002065044281310_profile&wvr=6&mod=weibotime",
    "sendAt": "1589442303000"
  },
  {
    "tbinfo": "ouid=5044281310",
    "mid": "4504507369205077",
    "text": "【全面封闭管理的吉林市：路面人少，大部分商铺停业】5月13日，吉林市全面实行封闭管理，客车火车票停售、早市关门、聚集性场所停业。14日，澎湃新闻直击封闭管理的吉林市，探访超市、步行街、药店等，关注当地生活出行。 O澎湃新闻的微博直播 . ​​​​",
    "link": "http://weibo.com/5044281310/J1TfWCCEZ?from=page_1002065044281310_profile&wvr=6&mod=weibotime",
    "sendAt": "1589441709000"
  },
  {
    "tbinfo": "ouid=5044281310",
    "mid": "4504505331705860",
    "text": "【女子醉卧马路，遭无证醉驾司机碾压】#醉卧马路女子遭醉驾司机碾压#近日，湖南湘潭。一女子横躺马路中央，随后一辆汽车从女子身上轧过。事发后，司机驾车逃逸，被群众追至家中拦截。该女子送医后无生命危险。据交警调查，司机王某武无证醉酒驾驶，车辆逾期未检。遭碾压女子黄某军当时也属饮酒状态。（ ​​​​...展开全文c",
    "link": "http://weibo.com/5044281310/J1TcF79LS?from=page_1002065044281310_profile&wvr=6&mod=weibotime",
    "sendAt": "1589441223000"
  },
  {
    "tbinfo": "ouid=5044281310",
    "mid": "4504500621214074",
    "text": "#受伤小狗被交警救下获名警缘# 【受伤小狗被交警救下送医，获名“警缘”】近日，四川绵阳。江油交警巡逻路上发现一条受伤的小狗，为免小狗受到二次伤害和危及行车安全，交警将其带走送医。目前小狗正在康复，救助中心给它起了新名字“警缘”。（素材来源：相关人士）°受伤小狗被交警救下送医，获名“警缘”  ​​​​...展开全文c",
    "link": "http://weibo.com/5044281310/J1T5455PQ?from=page_1002065044281310_profile&wvr=6&mod=weibotime",
    "sendAt": "1589440100000"
  },
  {
    "tbinfo": "ouid=5044281310",
    "mid": "4504498732763419",
    "text": "【国务院联防联控机制介绍方舱医院集中收治工作情况】5月14日15时，国务院联防联控机制召开新闻发布会，介绍方舱医院集中收治工作情况，请相关医疗和护理专家回答媒体提问。 L澎湃新闻的微博视频 . ​​​​",
    "link": "http://weibo.com/5044281310/J1T21bATh?from=page_1002065044281310_profile&wvr=6&mod=weibotime",
    "sendAt": "1589439650000"
  },
  {
    "tbinfo": "ouid=5044281310",
    "mid": "4504495263957761",
    "text": "【特朗普欲尽快重开学校，不接受福奇警告】#特朗普称美国学校应尽快复课#5月13日，美国总统特朗普表示应尽快重开学校，他称新冠病毒对年轻人的影响非常小。他还驳斥传染病学专家福奇对秋季重开学校感到担忧的看法，称该观点不可接受。（视频来源：CNN CBS）°特朗普欲尽快重开学校，不接受福奇警告 L澎湃新闻的微博视频 ​​​​",
    "link": "http://weibo.com/5044281310/J1SWqgBAR?from=page_1002065044281310_profile&wvr=6&mod=weibotime",
    "sendAt": "1589438823000"
  },
  {
    "tbinfo": "ouid=5044281310",
    "mid": "4504490394678049",
    "text": "【#云南安宁山火明火被扑灭#：五千多人扑救，过火面积170公顷】5月14日13时许，澎湃新闻从云南省森林消防总队获悉，截至14日凌晨1时10分，安宁青龙街道双湄村山神坝森林火灾明火全部扑灭。本次森林火灾过火面积共170.1公顷（安宁区域110公顷，禄丰区域60.1公顷），先后动用森林消防队伍、地方放专业扑 ​​​​...展开全文c",
    "link": "http://weibo.com/5044281310/J1SOzjCYp?from=page_1002065044281310_profile&wvr=6&mod=weibotime",
    "sendAt": "1589437662000"
  },
  {
    "tbinfo": "ouid=5044281310",
    "mid": "4504484878954326",
    "text": "【上海市政府通报疫情防控工作5月14日发布会】5月14日14时，上海市政府召开第77场疫情防控工作发布会，邀请市卫生健康委、浦东新区以及相关街镇、医院负责人介绍情况。 L澎湃新闻的微博视频 . ​​​​",
    "link": "http://weibo.com/5044281310/J1SFFBzqC?from=page_1002065044281310_profile&wvr=6&mod=weibotime",
    "sendAt": "1589436347000"
  },
  {
    "tbinfo": "ouid=5044281310",
    "mid": "4504484694945533",
    "text": "【放心卖萌！#成都大熊猫全部接受核酸检测#：结果全部是阴性】成都大熊猫繁育研究基地主任张志和表示，看到纽约动物园有老虎、狮子感染新冠病毒后，立即对熊猫进行了采样，经过权威机构的核酸检测，所有熊猫全部是阴性，没有问题。@央视网视频 L小央视频的秒拍视频 ​​​​",
    "link": "http://weibo.com/5044281310/J1SFnkKyF?from=page_1002065044281310_profile&wvr=6&mod=weibotime",
    "sendAt": "1589436303000"
  },
  {
    "tbinfo": "ouid=5044281310",
    "mid": "4504477870445614",
    "text": "【南京自建快递柜小区物业公司：化解丰巢风波，物业需积极作为】#南京部分小区自建快递柜#丰巢的一纸超时收费通知，引发了各方持续多日的争论。而在收费之争以外，江苏南京的部分小区自建快递柜的尝试已进行了多年，这些由物业公司自建的快递柜自运营开始就没有向业主收取任何费用。南京一物业公司相关 ​​​​...展开全文c",
    "link": "http://weibo.com/5044281310/J1Sun1RVk?from=page_1002065044281310_profile&wvr=6&mod=weibotime",
    "sendAt": "1589434676000"
  },
  {
    "tbinfo": "ouid=5044281310",
    "mid": "4504471454133815",
    "text": "【#成都发现超6000座各朝古墓#，时间轴从战国到明清】5月14日，四川成都。成都文物考古研究院公布，新川创新科技园有6000多座古墓，包括崖墓、砖室墓等多种类型，时间轴从战国延续到明清，并发掘出了大量遗物。四川观察°成都现六千多座古墓，时间轴从战国到明清 L澎湃新闻的微博视频 ​​​​",
    "link": "http://weibo.com/5044281310/J1Sk1hlor?from=page_1002065044281310_profile&wvr=6&mod=weibotime",
    "sendAt": "1589433146000"
  },
  {
    "tbinfo": "ouid=5044281310",
    "mid": "4504464852375227",
    "text": "【#美国17州超180名儿童患罕见综合征#，或与新冠有关】5月13日，外媒报道称美国17州超180例儿童患有罕见多系统炎症综合征，部分患儿确诊新冠，纽约州已有3例死亡。美国医学界现怀疑此综合征与新冠肺炎相关。（视频来源： CBS,CBSN,REUTERS）°美国百名儿童患罕见综合征，或与新冠有关  L澎湃新闻的微博视频 ​​​​",
    "link": "http://weibo.com/5044281310/J1S9n9XU7?from=page_1002065044281310_profile&wvr=6&mod=weibotime",
    "sendAt": "1589431572000"
  },
  {
    "tbinfo": "ouid=5044281310",
    "mid": "4504459282152450",
    "text": "#女子果园产女后弃婴#【29岁女子龙眼地产女，“感到害怕”弃婴】5月12日，海南乐东。工人在龙眼地里发现一名未剪脐带的女婴，仅被树叶掩盖身体。自称系母亲的29岁女子称，产娃后感到害怕，慌忙离开。民政局人员称，女婴身体无大碍。°29岁女子龙眼地产女，“感到害怕”弃婴 L澎湃新闻的微博视频 ​​​​",
    "link": "http://weibo.com/5044281310/J1S0o91WW?from=page_1002065044281310_profile&wvr=6&mod=weibotime",
    "sendAt": "1589430244000"
  },
  {
    "tbinfo": "ouid=5044281310",
    "mid": "4504452487270659",
    "text": "【#徐州沛县一处麦田发现女尸#，警方调查是否为情杀】5月13日，江苏徐州。沛县某村附近一处麦田里，发现一具女尸。当地村民称死者30岁左右，疑因彩礼引发的情杀。王店派出所称接警后已赶往现场，是否为情杀仍在调查中。（素材来源：相关人士）°徐州一处麦田发现女尸，警方调查是否为情杀 L澎湃新闻的微博视频 ​​​​",
    "link": "http://weibo.com/5044281310/J1RPquvqH?from=page_1002065044281310_profile&wvr=6&mod=weibotime",
    "sendAt": "1589428623000"
  },
  {
    "tbinfo": "ouid=5044281310",
    "mid": "4504446694258486",
    "text": "【陕西#女子托人给娃办上学被骗20万#，孩子耽搁了5年】2013年，女子马翠(化名)认识了李某，彼此很快信任。2016年，马翠的女儿该上小学了，李某说可以少花些钱进西安东郊一所小学，马翠便决定托他办上学。然而就此噩梦开始，五年来，李某并未办成功，每天都说“快了、下周、明天，保证解决”，5年里，被 ​​​​...展开全文c",
    "link": "http://weibo.com/5044281310/J1RG5hRPg?from=page_1002065044281310_profile&wvr=6&mod=weibotime",
    "sendAt": "1589427243000"
  },
  {
    "tbinfo": "ouid=5044281310",
    "mid": "4504440906365533",
    "text": "【被患者砍伤114天后陶勇恢复出诊，将于下周二指导手术】#陶勇医生下周将指导手术#5月13日晚间，北京朝阳医院眼科医生陶勇向记者证实，其已经于当天正式恢复出诊。他用“内心平静又感动”形容了自己自受伤以来，第一天出诊的感受。陶勇说，当天遇到一个病人，疫情期间眼睛发生了严重病变，已经跑了很多 ​​​​...¡查看图片展开全文c",
    "link": "http://weibo.com/5044281310/J1RwKqHXT?from=page_1002065044281310_profile&wvr=6&mod=weibotime",
    "sendAt": "1589425863000"
  },
  {
    "tbinfo": "ouid=5044281310",
    "mid": "4504435873014329",
    "text": "【#坠入黄河一家四口已找到3人遗体#，家属发帖有偿搜寻最后一人】记者从坠河者家属处获悉，截至5月13日下午，距陕西一家4口坠河已过去11天，目前已找到3人，另1人王某某仍在搜救中，目前家属已发布寻人帖，凡提供信息或发现王某某遗体者，将答谢5千元至1万元。红星新闻°坠入黄河一家四口已找到3人遗体，家属发帖有... ​​​​",
    "link": "http://weibo.com/5044281310/J1RoDcEad?from=page_1002065044281310_profile&wvr=6&mod=weibotime",
    "sendAt": "1589424663000"
  },
  {
    "tbinfo": "ouid=5044281310",
    "mid": "4504430714381589",
    "text": "【#女子称遭跑步机电击致尿失禁#，涉事健身房已停业】近日，浙江杭州。钟女士反映，在一家健身房的跑步机旁拉伸时遭遇电击导致小便失禁。健身房负责人称，怀疑是女子操作不当。目前涉事健身房已暂时停业。（素材来源：相关人士）°女子称遭跑步机电击致尿失禁，涉事健身房已停业 L澎湃新闻的微博视频 ​​​​",
    "link": "http://weibo.com/5044281310/J1RgjinQN?from=page_1002065044281310_profile&wvr=6&mod=weibotime",
    "sendAt": "1589423433000"
  },
  {
    "tbinfo": "ouid=5044281310",
    "mid": "4504425685093872",
    "text": "【羚牛疑求偶失败，闯入村庄猛撞铁门】#羚牛疑求偶失败后闯入村庄#5月12日，陕西西安。一头羚牛跑进村庄冲撞铁门等，被麻醉后送至救助站。工作人员称该羚牛为雄性，是国家一级保护动物，疑求偶失败后离群进村，将根据其身体情况决定是否放生。（素材来源：减影）°羚牛疑求偶失败，闯入村庄猛撞铁门  ​​​​...展开全文c",
    "link": "http://weibo.com/5044281310/J1R8cln9e?from=page_1002065044281310_profile&wvr=6&mod=weibotime",
    "sendAt": "1589422234000"
  },
  {
    "tbinfo": "ouid=5044281310",
    "mid": "4504420472267247",
    "text": "【#110个新冠肺炎疫苗竞速#：8个进入临床试验，瞄准9月紧急使用】#110个新冠肺炎疫苗正在研发#新冠病毒研发竞赛，走在前列的依然是中美。截至5月11日，世界卫生组织的官网上已经备案了110个正在研发的新冠肺炎疫苗，其中已进入临床试验的共有8个。澎湃新闻记者梳理发现，这8个已经进入临床试验的疫苗中 ​​​​...展开全文c",
    "link": "http://weibo.com/5044281310/J1QZN9vOv?from=page_1002065044281310_profile&wvr=6&mod=weibotime",
    "sendAt": "1589420991000"
  },
  {
    "tbinfo": "ouid=5044281310",
    "mid": "4504414196902780",
    "text": "【#对丰巢说不的上海小区已达116个#】5月13日，业委会参与者平台“众蚁社区”上参与“对丰巢说不”的上海小区已有116个。众蚁社区的负责人韩冰表示：联名对丰巢说不，并非要抵制丰巢，只是希望能沟通。（视频来源：网络综合）°“对丰巢说不”的上海小区已达116个  L澎湃新闻的微博视频 ​​​​",
    "link": "http://weibo.com/5044281310/J1QPFsXJa?from=page_1002065044281310_profile&wvr=6&mod=weibotime",
    "sendAt": "1589419495000"
  },
  {
    "tbinfo": "ouid=5044281310",
    "mid": "4504408211539435",
    "text": "【不顾疫情风险，#韩国民众聚集疯抢香奈儿#】5月13日，韩国媒体报道称由于奢侈品牌“香奈儿”将从14日起上调全球产品价格，引发抢购热潮。尽管韩国正因“夜店聚集性感染”面临疫情二次暴发的风险，但大批民众仍涌向香奈儿专柜排队购买。（视频来源：综合网络）°不顾疫情风险，韩国民众聚集疯抢香奈儿   ​​​​...展开全文c",
    "link": "http://weibo.com/5044281310/J1QG16stB?from=page_1002065044281310_profile&wvr=6&mod=weibotime",
    "sendAt": "1589418068000"
  },
  {
    "tbinfo": "ouid=5044281310",
    "mid": "4504404143315032",
    "text": "【#31省区市新增3例确诊病例#，#31省区市新增12例无症状感染者#】5月13日0—24时，31个省（自治区、直辖市）和新疆生产建设兵团报告新增确诊病例3例，均为本土病例（辽宁2例，吉林1例）；无新增死亡病例；无新增疑似病例。当日新增治愈出院病例6例，解除医学观察的密切接触者387人，重症病例减少1例。 ​​​​...展开全文c",
    "link": "http://weibo.com/5044281310/J1QzsdUog?from=page_1002065044281310_profile&wvr=6&mod=weibotime",
    "sendAt": "1589417098000"
  },
  {
    "tbinfo": "ouid=5044281310",
    "mid": "4504400016748002",
    "text": "【#吉林市公布新增病例行动轨迹#】据吉林市卫健委，5月13日0-24时，全市新增本地确诊病例1例。#吉林新增1例本土确诊#详情如下：    新增本地确诊病例，女，1967年出生，吉林市人，与5月11日吉林市通报确诊病例3有关联，住址为吉林市丰满区红旗街四合田园小区。　　4月26日至5月2日每天4时至8时骑电瓶 ​​​​...展开全文c",
    "link": "http://weibo.com/5044281310/J1QsNsjsK?from=page_1002065044281310_profile&wvr=6&mod=weibotime",
    "sendAt": "1589416113000"
  },
  {
    "tbinfo": "ouid=5044281310",
    "mid": "4504399412583489",
    "text": "【#辽宁新增2例本土病例#，均为沈阳市报告病例】5月13日0时至24时，辽宁省新增2例本土新冠肺炎确诊病例（其中1例为无症状感染者转为确诊病例），均为沈阳市报告病例，均属轻型病例。无新增治愈出院病例。全省累计报告本土确诊病例128例，治愈出院123例，死亡2例，在院治疗3例。O网页链接 ​ ​​​​...展开全文c",
    "link": "http://weibo.com/5044281310/J1QrPaQ5b?from=page_1002065044281310_profile&wvr=6&mod=weibotime",
    "sendAt": "1589415970000"
  },
  {
    "tbinfo": "ouid=5044281310",
    "mid": "4504389836407493",
    "text": "【#美国确诊病例超过138万#】据美国约翰斯·霍普金斯大学发布的全球新冠肺炎数据实时统计系统，截至美国东部时间5月13日晚6时，全美共报告新冠肺炎确诊1385639例，死亡83715例。过去24小时，美国新增确诊19289例，新增死亡1610例。在疫情最为严重的纽约州，13日累计确诊达到340661例,累计死亡27409例。 ​​​​...展开全文c",
    "link": "http://weibo.com/5044281310/J1QcnqSSF?from=page_1002065044281310_profile&wvr=6&mod=weibotime",
    "sendAt": "1589413686000"
  },
  {
    "tbinfo": "ouid=5044281310",
    "mid": "4504249143067001",
    "text": "#车主让外卖员赔1元劝其莫违规# 【外卖员闯红灯躲交警刮花轿车，车主让赔1元劝其莫违规】5月8日，江苏南通。一名外卖小哥闯红灯遭交警拦截，情急之下掉头，不小心撞到路边轿车，车主最终只让外卖员赔付1元，提醒其下次不要再违规。外卖员表示将铭记一辈子。°外卖员闯红灯躲交警刮花轿车，车主让赔1元劝... L澎湃新闻的微博视频 ​​​​",
    "link": "http://weibo.com/5044281310/J1MxscRRL?from=page_1002065044281310_profile&wvr=6&mod=weibotime",
    "sendAt": "1589380143000"
  },
  {
    "tbinfo": "ouid=5044281310",
    "mid": "4504243606329772",
    "text": "【#绍兴越城城管回应抢狗# ：烈犬未办证无牵绳，实施收容】5月13日，浙江省绍兴市越城区综合行政执法局微信公众号“越城城管”发布通报回应网传“城管暴力抢夺农民工犬只”视频，称该犬只为德国牧羊犬，是未办理养犬证的当地禁养烈性犬种，犬管中队工作人员和民警劝导犬主，但犬主拒不配合，犬主多次辱 ​​​​...展开全文c",
    "link": "http://weibo.com/5044281310/J1MowqyF6?from=page_1002065044281310_profile&wvr=6&mod=weibotime",
    "sendAt": "1589378823000"
  },
  {
    "tbinfo": "ouid=5044281310",
    "mid": "4504238439340018",
    "text": "【#印度女子返乡途中分娩# ，歇两小时又走百公里】据今日印度5月13日报道，一名怀有身孕的女劳工在步行回乡途中产下一子。在分娩完休息两个小时后，又步行了150公里。目前，这对母子已被当地政府送往医院接受治疗。（视频来源 综合网络）°印度女子返乡途中分娩，歇两小时又走百公里  L澎湃新闻的微博视频 ​​​​",
    "link": "http://weibo.com/5044281310/J1MgbDbLs?from=page_1002065044281310_profile&wvr=6&mod=weibotime",
    "sendAt": "1589377591000"
  },
  {
    "tbinfo": "ouid=5044281310",
    "mid": "4504231526076730",
    "text": "【被砍伤的#陶勇医生恢复出诊# 】据@儿科医生王师尧 ，今天，被砍伤的北京朝阳医院眼科医生陶勇，恢复出诊。1月20日，陶勇医生出诊时，被一男子持刀砍伤。 ​​​​°被砍伤的陶勇医生恢复出诊 ​​​​¡查看图片",
    "link": "http://weibo.com/5044281310/J1M52puPM?from=page_1002065044281310_profile&wvr=6&mod=weibotime",
    "sendAt": "1589375943000"
  },
  {
    "tbinfo": "ouid=5044281310",
    "mid": "4504228335154254",
    "text": "【1106万元！#日本将全球最贵药品纳入医保# 】5月13日，日本决定将全球最贵基因药品Zolgensma纳入医保范围，拟定单价1.67亿日元（约1106万元人民币）。该药用于治疗罕见遗传病脊髓性肌肉萎缩症。（视频来源 综合网络）°1106万元！日本将全球最贵药品纳入医保  L澎湃新闻的微博视频 ​​​​",
    "link": "http://weibo.com/5044281310/J1LZTlCR8?from=page_1002065044281310_profile&wvr=6&mod=weibotime",
    "sendAt": "1589375182000"
  },
  {
    "tbinfo": "ouid=5044281310",
    "mid": "4504220696765729",
    "text": "【小学生上网课后看直播打赏，花掉爸爸彩礼】#小学生花10万元打赏主播# 近日，湖北襄阳。一名老人为儿子筹备再婚，取钱发现卡中10万元钱只剩几百。原来是9岁孙女上网课后看直播，将钱打赏给了一名主播。该网络平台客服称核实后会退款。（素材来源： 相关人士）°小学生上网课后看直播打赏，花掉爸爸彩礼  ​​​​...展开全文c",
    "link": "http://weibo.com/5044281310/J1LNzso4F?from=page_1002065044281310_profile&wvr=6&mod=weibotime",
    "sendAt": "1589373361000"
  },
  {
    "tbinfo": "ouid=5044281310",
    "mid": "4504209233739595",
    "text": "#男子跳桥轻生被公交车接住#【长沙一男子跳桥，落地瞬间被公交车接住】5月13日，湖南长沙。一男子跳桥轻生，落地瞬间被路过的公交车接住，落到车顶。随后男子被赶来的消防员救下。据了解，男子受轻微伤，已被送往医院救治。（素材来源：相关人士）°长沙一男子跳桥，落地瞬间被公交车接住 L澎湃新闻的微博视频 ​​​​",
    "link": "http://weibo.com/5044281310/J1Lv5fGQ3?from=page_1002065044281310_profile&wvr=6&mod=weibotime",
    "sendAt": "1589370628000"
  },
  {
    "tbinfo": "ouid=5044281310",
    "mid": "4504203131798682",
    "text": "【#张文宏分享上海防疫经验#：尽早发现疑似病例，尽快诊断隔离】5月13日晚上6点，中国-英国-非洲合作防控新冠肺炎疫情视频连线开始。中国驻英大使刘晓明、中国疾控中心流行病首席专家吴尊友、复旦大学华山医院教授张文宏等出席。张文宏介绍，上海经验是尽早发现所有疑似病例，并且进行尽快地诊断和隔离 ​​​​...¡查看图片展开全文c",
    "link": "http://weibo.com/5044281310/J1Llf7xV0?from=page_1002065044281310_profile&wvr=6&mod=weibotime",
    "sendAt": "1589369173000"
  },
  {
    "tbinfo": "ouid=5044281310",
    "mid": "4504196696546768",
    "text": "【#中传坠楼研究生导师回应#：截图被断章取义】4月30日，中传研究生黄某怡跳楼自杀。5月12日，其导师薛燕平回应，心情很悲痛，并公布聊天记录，称网传截图断章取义。对未给黄某怡论文签字送审一事，以及二人论文选题观点不同等问题，薛燕平未作说明。（素材来源：相关人士）°中传坠楼女研究生导师：截图被断章取义  ​​​​...展开全文c",
    "link": "http://weibo.com/5044281310/J1LaRrt72?from=page_1002065044281310_profile&wvr=6&mod=weibotime",
    "sendAt": "1589367639000"
  },
  {
    "tbinfo": "ouid=5044281310",
    "mid": "4504191416782541",
    "text": "【#俄产呼吸机遭美国退货#，短路起火在俄已致6死】5月12日路透社报道，在俄罗斯产的一款呼吸机发生短路起火致6人死亡后，美国纽约州和新泽西州表示，已将此前俄罗斯赠送的同款呼吸机退回联邦政府，这批机器从未被使用。（视频来源 RT）°俄产呼吸机遭美国退货，短路起火在俄已致6死  L澎湃新闻的微博视频 ​​​​",
    "link": "http://weibo.com/5044281310/J1L2lssrP?from=page_1002065044281310_profile&wvr=6&mod=weibotime",
    "sendAt": "1589366380000"
  },
  {
    "tbinfo": "ouid=5044281310",
    "mid": "4504183208808740",
    "text": "【#韩国N号房创建人身份照片公开#：建筑学专业大学生，性格内向】海外网5月13日消息，据韩联社报道，韩国警方当日开会决定公开“N号房”创建人“godgod”的个人信息：原名文亨旭（音译），24岁，是一名建筑学专业的大学生。警方5月18日把文亨旭移交检方时，会将其公开示众。文亨旭是“N号房”聊天群的 ​​​​...展开全文c",
    "link": "http://weibo.com/5044281310/J1KP6AXys?from=page_1002065044281310_profile&wvr=6&mod=weibotime",
    "sendAt": "1589364423000"
  },
  {
    "tbinfo": "ouid=5044281310",
    "mid": "4504178266810309",
    "text": "#贝克汉姆快秃头了# 【这一刻，万人迷小贝也太“秃然”了】近日，45岁的贝克汉姆出门时被外媒拍到，令人惊讶的是，“万人迷”发量日渐稀少，甚至有了秃发的趋势。值得一提的是，两年前小贝曾被曝接受了植发术。（来源网络）°这一刻，万人迷小贝也太“秃然”了 L澎湃新闻的微博视频 ​​​​",
    "link": "http://weibo.com/5044281310/J1KH8szFH?from=page_1002065044281310_profile&wvr=6&mod=weibotime",
    "sendAt": "1589363245000"
  },
  {
    "tbinfo": "ouid=5044281310",
    "mid": "4504172638975662",
    "text": "#错换人生家属与医院协商无果#【错换人生28年续：院方称答应条件后能借支5万元精神赔偿】5月13日，河南开封。错换人生28年事件，许女士称，家属与医院先后协商三次无果，将继续进行维权。她称，院方提出让家属在20日前在开封提起诉讼，借支费用从精神损失费中扣除。#错换人生28年事件医患调解无果#  ​​​​...展开全文c",
    "link": "http://weibo.com/5044281310/J1Ky3BEYK?from=page_1002065044281310_profile&wvr=6&mod=weibotime",
    "sendAt": "1589361903000"
  },
  {
    "tbinfo": "ouid=5044281310",
    "mid": "4504167459078150",
    "text": "【#推特允许员工永久居家办公# ，还发一千美元】据CNN5月12日报道，推特成为首家允许部分员工永久性居家办公的大型科技公司，其称近几个月来看居家办公可以推广。员工还将获得1000美元补贴，用于购买必要设备。（视频来源：CNN及综合网络）°推特允许员工永久居家办公，还发一千美元 L澎湃新闻的微博视频 ​​​​",
    "link": "http://weibo.com/5044281310/J1KpHC5DM?from=page_1002065044281310_profile&wvr=6&mod=weibotime",
    "sendAt": "1589360668000"
  },
  {
    "tbinfo": "ouid=5044281310",
    "mid": "4504161825100771",
    "text": "#检票员遭男子吐口水后染新冠身亡#【英国一检票员遭男子故意吐口水，染疫两周后身亡】5月12日英媒报道，伦敦一名铁路检票员当值期间被一名自称患有新冠的男子吐口水后，于4月5日因新冠死亡。英国交通警察局已对该事件展开调查，并呼吁民众提供线索。（视频来源 Skynews ITV）°英国一检票员遭男子故意吐口水，染疫两周后身亡  ​​​​...展开全文c",
    "link": "http://weibo.com/5044281310/J1KgCloWv?from=page_1002065044281310_profile&wvr=6&mod=weibotime",
    "sendAt": "1589359325000"
  },
  {
    "tbinfo": "ouid=5044281310",
    "mid": "4504159351945339",
    "text": "2020百度移动生态大会在“云”上召开，透露了移动生态下半年的核心打法。随着创作者运营平台打通、服务属性日益强化，可以看到，百度移动生态正在日臻完善，正在焕发新的活力。点击视频，3分钟回顾更多大会精彩内容。  L澎湃新闻的微博视频 ​​​​",
    "link": "http://weibo.com/5044281310/J1KcD8a4r?from=page_1002065044281310_profile&wvr=6&mod=weibotime",
    "sendAt": "1589358735000"
  },
  {
    "tbinfo": "ouid=5044281310",
    "mid": "4504154347498062",
    "text": "【外媒：#瑞幸CEO和COO被终止职务# 】5月12日，据CNBC消息，瑞幸咖啡宣布调整董事会和高级管理层，CEO钱治亚和COO刘剑被终止职务。后总裁办发布全员信为近期风波道歉，表示门店将正常运行。（素材来源 网络 相关人士）°外媒：瑞幸CEO和COO被终止职务 L澎湃新闻的微博视频 ​​​​",
    "link": "http://weibo.com/5044281310/J1K4yvsAu?from=page_1002065044281310_profile&wvr=6&mod=weibotime",
    "sendAt": "1589357541000"
  },
  {
    "tbinfo": "ouid=5044281310",
    "mid": "4504148730911232",
    "text": "【#福州大学一教师被学生举报性侵#，校方：高度重视，成立调查组】#福州大学回应教师被举报性侵多名女生# 5月13日，针对张姓教师被学生举报性侵一事，福州大学党委宣传部相关工作人员向澎湃新闻表示，今天校方已成立调查组，介入该事件。13日，有当事人向澎湃新闻表示，该事件有多名受害者，此前报警未 ​​​​...展开全文c",
    "link": "http://weibo.com/5044281310/J1JVv3P3i?from=page_1002065044281310_profile&wvr=6&mod=weibotime",
    "sendAt": "1589356203000"
  },
  {
    "tbinfo": "ouid=5044281310",
    "mid": "4504143702097103",
    "text": "#陕西一中学教师殴打2名未成年人# 【陕西潼关一中学教师殴打2名未成年人，官方：责令其停职反省】5月12日上午，陕西潼关的李女士向记者反映，她家孩子今年11岁，5月9日19点20分左右，孩子在小区内骑自行车玩耍，与魏某的妻子发生碰撞，两人均摔倒在地。“令人没有想到的是，他没有问清原委，直接冲上去 ​​​​...展开全文c",
    "link": "http://weibo.com/5044281310/J1JNo8Nyf?from=page_1002065044281310_profile&wvr=6&mod=weibotime",
    "sendAt": "1589355004000"
  }
]